{
    "0xedb6f3a4a1ebc511f7fe9bd4f2cd4219ca0a3cf4": {
        "StartingPointWrittenToContract": 735,
        "DestinationWrittenToContract": 2897,
        "FoundIdleCarsNearby": 1,
        "FoundTheMostNearbyCar": 18,
        "TheMostNearbyCarIsSelected": 1836,
        "PassengerOnBoard": 8040,
        "PassengerArriveAtDestination": 2653,
        "PassengerPaysAndGetsOff": 2135
    },
    "0xbd2f3e025a8f0b0d8bb9f64ef60980ebb27e8d5d": {
        "StartingPointWrittenToContract": 1415,
        "DestinationWrittenToContract": 2143,
        "FoundIdleCarsNearby": 1,
        "FoundTheMostNearbyCar": 20,
        "TheMostNearbyCarIsSelected": 6356,
        "PassengerOnBoard": 3256,
        "PassengerArriveAtDestination": 2123,
        "PassengerPaysAndGetsOff": 1739
    },
    "0xabd6b57b7d198796947bc03e4f5bd911813caada": {
        "StartingPointWrittenToContract": 6931,
        "DestinationWrittenToContract": 596,
        "FoundIdleCarsNearby": 3,
        "FoundTheMostNearbyCar": 26035,
        "TheMostNearbyCarConflict": 2682,
        "TheMostNearbyCarIsSelected": 2611,
        "PassengerOnBoard": 3337,
        "PassengerArriveAtDestination": 6698,
        "PassengerPaysAndGetsOff": 5516
    },
    "0x62119c27e0081b14e6e0c596603d21eaa6d6452b": {
        "StartingPointWrittenToContract": 3937,
        "DestinationWrittenToContract": 591,
        "FoundIdleCarsNearby": 2,
        "FoundTheMostNearbyCar": 22020,
        "TheMostNearbyCarConflict": 1105,
        "TheMostNearbyCarIsSelected": 2691,
        "PassengerOnBoard": 4190,
        "PassengerArriveAtDestination": 2939,
        "PassengerPaysAndGetsOff": 470
    },
    "0xc265c858c1186113b2d830e6f46f6d95142e9750": {
        "StartingPointWrittenToContract": 933,
        "DestinationWrittenToContract": 591,
        "FoundIdleCarsNearby": 5,
        "FoundTheMostNearbyCar": 46,
        "TheMostNearbyCarIsSelected": 2609,
        "PassengerOnBoard": 3865,
        "PassengerArriveAtDestination": 2570,
        "PassengerPaysAndGetsOff": 1734
    },
    "0x03875bcc0db199992266825e2c1cf0f5bfc200d2": {
        "StartingPointWrittenToContract": 1188,
        "DestinationWrittenToContract": 2129,
        "FoundIdleCarsNearby": 1,
        "FoundTheMostNearbyCar": 25,
        "TheMostNearbyCarIsSelected": 1711,
        "PassengerOnBoard": 4302,
        "PassengerArriveAtDestination": 3168,
        "PassengerPaysAndGetsOff": 2571
    },
    "0xf0ce9fe96ac15405e4fd51a62cbdbdaef2d36372": {
        "StartingPointWrittenToContract": 1572,
        "DestinationWrittenToContract": 910,
        "FoundIdleCarsNearby": 1,
        "FoundTheMostNearbyCar": 15,
        "TheMostNearbyCarIsSelected": 2129,
        "PassengerOnBoard": 4907,
        "PassengerArriveAtDestination": 2559,
        "PassengerPaysAndGetsOff": 1253
    },
    "0x1bdf42d9a37b5b5c5a3bc09cadfade23d075791a": {
        "StartingPointWrittenToContract": 1624,
        "DestinationWrittenToContract": 1728,
        "FoundIdleCarsNearby": 5,
        "FoundTheMostNearbyCar": 24,
        "TheMostNearbyCarIsSelected": 3150,
        "PassengerOnBoard": 3815,
        "PassengerArriveAtDestination": 1787,
        "PassengerPaysAndGetsOff": 3268
    },
    "0x3449a20e1b4700ffd4dd49f0fc14bcac44fee63c": {
        "StartingPointWrittenToContract": 493,
        "DestinationWrittenToContract": 3042,
        "FoundIdleCarsNearby": 3,
        "FoundTheMostNearbyCar": 19,
        "TheMostNearbyCarIsSelected": 2541,
        "PassengerOnBoard": 3043,
        "PassengerArriveAtDestination": 3256,
        "PassengerPaysAndGetsOff": 2857
    },
    "0xd2ed0cb17fd847c8aa8bc8e9ed3870481ede088b": {
        "StartingPointWrittenToContract": 531,
        "DestinationWrittenToContract": 2562,
        "FoundIdleCarsNearby": 5,
        "FoundTheMostNearbyCar": 33,
        "TheMostNearbyCarIsSelected": 1215,
        "PassengerOnBoard": 5051,
        "PassengerArriveAtDestination": 2848,
        "PassengerPaysAndGetsOff": 2239
    },
    "0x5227daf8db7c57d268979df21ba9ee9c93d26712": {
        "StartingPointWrittenToContract": 687,
        "DestinationWrittenToContract": 1670,
        "FoundIdleCarsNearby": 1,
        "FoundTheMostNearbyCar": 25,
        "TheMostNearbyCarIsSelected": 924,
        "PassengerOnBoard": 5945,
        "PassengerArriveAtDestination": 2220,
        "PassengerPaysAndGetsOff": 937
    },
    "0xb658cbd857f52f9705fbecf9b30cf827dd8c81a8": {
        "StartingPointWrittenToContract": 305,
        "DestinationWrittenToContract": 3094,
        "FoundIdleCarsNearby": 3,
        "FoundTheMostNearbyCar": 13,
        "TheMostNearbyCarIsSelected": 2838,
        "PassengerOnBoard": 3154,
        "PassengerArriveAtDestination": 2499,
        "PassengerPaysAndGetsOff": 668
    },
    "0x5895ef03d8c36b9a53b4f961cd1345ed0bd79fa3": {
        "StartingPointWrittenToContract": 396,
        "DestinationWrittenToContract": 2854,
        "FoundIdleCarsNearby": 3,
        "FoundTheMostNearbyCar": 24,
        "TheMostNearbyCarIsSelected": 2205,
        "PassengerOnBoard": 3424,
        "PassengerArriveAtDestination": 663,
        "PassengerPaysAndGetsOff": 3755
    },
    "0x4093777e3bf0a104ef5576011a965c58a206b69b": {
        "StartingPointWrittenToContract": 1531,
        "DestinationWrittenToContract": 1279,
        "FoundIdleCarsNearby": 2,
        "FoundTheMostNearbyCar": 22,
        "TheMostNearbyCarIsSelected": 694,
        "PassengerOnBoard": 3048,
        "PassengerArriveAtDestination": 3748,
        "PassengerPaysAndGetsOff": 1143
    },
    "0x7906b337632876b8050f55ee5b57228f02972fa3": {
        "StartingPointWrittenToContract": 529,
        "DestinationWrittenToContract": 2380,
        "FoundIdleCarsNearby": 2,
        "FoundTheMostNearbyCar": 31,
        "TheMostNearbyCarIsSelected": 633,
        "PassengerOnBoard": 4891,
        "PassengerArriveAtDestination": 518,
        "PassengerPaysAndGetsOff": 3972
    },
    "0x3b49b8eb1d9d3c28242b97c135379e0e32468fb9": {
        "StartingPointWrittenToContract": 573,
        "DestinationWrittenToContract": 3753,
        "FoundIdleCarsNearby": 1,
        "FoundTheMostNearbyCar": 19,
        "TheMostNearbyCarIsSelected": 1121,
        "PassengerOnBoard": 4488,
        "PassengerArriveAtDestination": 7724,
        "PassengerPaysAndGetsOff": 1763
    }
}